selfless.py
selfless-0.0.3.dist-info/DESCRIPTION.rst
selfless-0.0.3.dist-info/LICENSE.txt
selfless-0.0.3.dist-info/METADATA
selfless-0.0.3.dist-info/RECORD
selfless-0.0.3.dist-info/WHEEL
selfless-0.0.3.dist-info/metadata.json
selfless-0.0.3.dist-info/top_level.txt
selfless-0.0.3.dist-info/zip-safe
