Metadata-Version: 2.0
Name: selfless
Version: 0.0.3
Summary: A small experimental module for implicit "self" support in Python (in some restricted contexts)
Home-page: https://github.com/PMeira/selfless
Author: Paulo Meira
Author-email: 10246101+PMeira@users.noreply.github.com
License: BSD
